pycryptoex/__init__.py
pycryptoex/__version__.py
pycryptoex/_cli.py
pycryptoex/py.typed
pycryptoex/base/exceptions.py
pycryptoex/base/exchange.py
pycryptoex/base/utils.py
pycryptoex/base/websocket.py
pycryptoex-0.6.2.dist-info/METADATA
pycryptoex-0.6.2.dist-info/WHEEL
pycryptoex-0.6.2.dist-info/entry_points.txt
pycryptoex-0.6.2.dist-info/licenses/LICENSE
pycryptoex-0.6.2.dist-info/RECORD
