Metadata-Version: 2.3
Name: pycryptoex
Version: 0.6.2
Summary: A library providing a clients for interacting with various APIs of cryptocurrency exchanges for trading and accessing market data
Project-URL: Homepage, https://github.com/ren3104/pycryptoex
Project-URL: Repository, https://github.com/ren3104/pycryptoex
Project-URL: Bug Tracker, https://github.com/ren3104/pycryptoex/issues
Author-email: ren3104 <2ren3104@gmail.com>
License: MIT
Keywords: altcoin,api,api-client,async,bitcoin,crypto,cryptocurrency,exchange,trade,trading,websocket
Classifier: Development Status :: 3 - Alpha
Classifier: Intended Audience :: Developers
Classifier: Intended Audience :: Financial and Insurance Industry
Classifier: License :: OSI Approved :: MIT License
Classifier: Operating System :: OS Independent
Classifier: Programming Language :: Python
Classifier: Programming Language :: Python :: 3
Classifier: Programming Language :: Python :: 3 :: Only
Classifier: Programming Language :: Python :: 3.9
Classifier: Programming Language :: Python :: 3.10
Classifier: Programming Language :: Python :: 3.11
Classifier: Programming Language :: Python :: 3.12
Classifier: Topic :: Software Development :: Libraries
Classifier: Topic :: Software Development :: Libraries :: Python Modules
Classifier: Typing :: Typed
Requires-Python: >=3.9
Requires-Dist: aiohttp>=3.3.0
Requires-Dist: typing-extensions>=4.0.0; python_version < '3.11'
Provides-Extra: crypto
Requires-Dist: pycryptodome; extra == 'crypto'
Provides-Extra: dev
Requires-Dist: pre-commit; extra == 'dev'
Requires-Dist: ruff; extra == 'dev'
Provides-Extra: fmt
Requires-Dist: mypy; extra == 'fmt'
Provides-Extra: speedup
Requires-Dist: orjson; extra == 'speedup'
